LICENSE.txt
MANIFEST.in
README.md
pyproject.toml
setup.cfg
src/backup_rsync_base/__init__.py
src/backup_rsync_base/backup_base.py
src/backup_rsync_base/build_info.py
src/backup_rsync_base/constants.py
src/backup_rsync_base/constants_version.py
src/backup_rsync_base.egg-info/PKG-INFO
src/backup_rsync_base.egg-info/SOURCES.txt
src/backup_rsync_base.egg-info/dependency_links.txt
src/backup_rsync_base.egg-info/requires.txt
src/backup_rsync_base.egg-info/top_level.txt