Metadata-Version: 2.4
Name: backup-rsync-base
Version: 0.1.2
Summary: A base class for supporting cross-platform backups using rsync
Author-email: "J. Arrizza" <cppgent0@gmail.com>
Maintainer-email: "J. Arrizza" <cppgent0@gmail.com>
License-Expression: MIT
Project-URL: Website, https://arrizza.com/python-backup-rsync-base
Project-URL: Source, https://bitbucket.org/arrizza-public/backup-rsync-base/src/master
Project-URL: Download, https://bitbucket.org/arrizza-public/backup-rsync-base/get/master.zip
Keywords: backup,rsync,maintenance
Classifier: Development Status :: 4 - Beta
Classifier: Environment :: Console
Classifier: Topic :: Utilities
Classifier: Intended Audience :: Developers
Classifier: Programming Language :: Python :: 3.10
Classifier: Programming Language :: Python :: 3.12
Requires-Python: >=3.9
License-File: LICENSE.txt
Requires-Dist: notify-client-server
Requires-Dist: falcon-logger
Dynamic: license-file
